_py4dgeo.cp313-win_amd64.pyd
py4dgeo/cloudcompare.py
py4dgeo/epoch.py
py4dgeo/fallback.py
py4dgeo/logger.py
py4dgeo/m3c2.py
py4dgeo/m3c2ep.py
py4dgeo/pbm3c2.py
py4dgeo/py4dgeo_python.cpp
py4dgeo/registration.py
py4dgeo/segmentation.py
py4dgeo/UpdateableZipFile.py
py4dgeo/util.py
py4dgeo/__init__.py
py4dgeo-0.8.0.data/platlib/libomp-a12116ba72d1d6820407cf30be23da04.dll
py4dgeo-0.8.0.data/platlib/msvcp140-a4c2229bdc2a2a630acdc095b4d86008.dll
py4dgeo-0.8.0.dist-info/DELVEWHEEL
py4dgeo-0.8.0.dist-info/entry_points.txt
py4dgeo-0.8.0.dist-info/METADATA
py4dgeo-0.8.0.dist-info/RECORD
py4dgeo-0.8.0.dist-info/WHEEL
py4dgeo-0.8.0.dist-info/licenses/COPYING.md
py4dgeo-0.8.0.dist-info/licenses/LICENSE.md
