Metadata-Version: 2.2
Name: py4dgeo
Version: 0.8.0
Summary: Library for change detection in 4D point cloud data
Maintainer-Email: Dominic Kempf <ssc@iwr.uni-heidelberg.de>
License: Permission is hereby granted, free of charge, to any person obtaining a copy of this software and associated documentation files (the "Software"), to deal in the Software without restriction, including without limitation the rights to use, copy, modify, merge, publish, distribute, sublicense, and/or sell copies of the Software, and to permit persons to whom the Software is furnished to do so, subject to the following conditions:
Classifier: Programming Language :: Python :: 3
Classifier: Programming Language :: C++
Classifier: Operating System :: OS Independent
Classifier: License :: OSI Approved :: MIT License
Classifier: Topic :: Scientific/Engineering :: GIS
Classifier: Intended Audience :: Science/Research
Requires-Python: >=3.8
Requires-Dist: dateparser
Requires-Dist: laspy[lazrs]<3.0,>=2.0
Requires-Dist: matplotlib
Requires-Dist: numpy
Requires-Dist: pooch
Requires-Dist: requests
Requires-Dist: seaborn
Requires-Dist: scikit-learn
Requires-Dist: vedo
Requires-Dist: xdg
Requires-Dist: psutil
